{
    "name": "Comida Criolla Ocho Vías",
    "address": "Avenida 1er Anillo 3km despues de San Agustin",
    "schedule": {
      "monday": {"open": "11:00", "close": "23:00"},
      "tuesday": {"open": "11:00", "close": "23:00"},
      "wednesday": {"open": "11:00", "close": "23:00"},
      "thursday": {"open": "11:00", "close": "23:00"},
      "friday": {"open": "11:00", "close": "23:00"},
      "saturday": {"open": "11:00", "close": "23:00"},
      "sunday": {"open": "11:00", "close": "23:00"}
    },
    "phone_number": "+5359107933",
    "website": {
      "website": null,
      "instagram": null,
      "facebook": null
    },
    "type_establishment": "restaurante",
    "specialty": "cubana",
    "parking": true,
    "reservations": true,
    "payment_methods": {
      "cash_national": true,
      "digital_transfer_national": true,
      "usd_cash": true,
      "usd_transfer": true,
      "mlc": true
    },
    "free_wifi": false,
    "delivery_areas": [
        null 
    ],
    "power_generator": "Sí" ,
    "capacity": "media",
    "menu": {
      "entrants": [
        {"name": "Croquetas de queso", "price": 500.00},
        {"name": "Tostones Rellenos", "price": 800.00},
        {"name": "Tostones Tradicionales", "price": 250.00},
        {"name": "Papas Fritas", "price": 800.00},
        {"name": "Platanos Fritos", "price": 200.00}
      ],
      "main_course": [
        {"name": "Bistec de Higado(460 gramos)", "price": 1600.00},
        {"name": "Higado Italiana(460 gramos)", "price": 1600.00},
        {"name": "Bistec de Cerdo(460 gramos)", "price": 2200.00},
        {"name": "Chuleta de Cerdo(460 gramos)", "price": 2200.00},
        {"name": "Fricase de Cerdo(430 gramos)", "price": 2500.00},
        {"name": "Masa Frita(430 gramos)", "price": 2200.00},
        {"name": "Fricase de Carnero(960 gramos)", "price": 2200.00},
        {"name": "Bistec Uruguayo)", "price": 2800.00},
        {"name": "Pescado Entero a la Marinera", "price": 2200.00},
        {"name": "Ropa Vieja(460 gramos)", "price": 2700.00},
        {"name": "Camaron Enchilado", "price": 2700.00},
        {"name": "Langosta Grille(690 gramos)", "price": 2700.00},
        {"name": "Langosta Enchilada(690 gramos)", "price": 2800.00},
        {"name": "Pescado Empanado", "price": 2500.00},
        {"name": "Enchilado de Cangrejo", "price": 1800.00},
        {"name": "Bistec de Pollo", "price": 2000.00},
        {"name": "Pechuga de Pollo", "price": 2500.00},
        {"name": "Costilla Frita o Fricase", "price": 2200.00}
      ],
      "garrison": [
        {"name": "Arroz Moro", "price": 200.00},
        {"name": "Ensalada Mixta", "price": 300.00}
      ],
      "desserts": [
        null
      ],
      "drinks": [
        null
      ]
    },
    "service_charge_percentage": 0 
}